Workbook

Sheet project
A1: attribute | B1: value
A2: project | B2: ssp-submission-workflow
A3: file_created | B3: 2024-12-17 08:10:51
A5: ssp-submission-workflow.url | B5: git@github.com:iiasa/ssp-submission-workflow
A6: ssp-submission-workflow.commit_hash | B6: 8c9ac62ec5b90382bf0d7ac679ae274b6aac992c
A7: ssp-submission-workflow.commit_timestamp | B7: 2024-12-17 08:09:58
A8: common-definitions.url | B8: https://github.com/IAMconsortium/common-definitions.git/
A9: common-definitions.commit_hash | B9: 99ec80c0e8473f6b172b07e18982bfdc4ae1a4d5
A10: common-definitions.commit_timestamp | B10: 2024-12-16 16:31:38

Sheet region
A1: region | B1: repository | C1: hierarchy | D1: description | E1: countries | F1: ar6 | G1: ssp | H1: navigate | I1: notes
A2: AIM 3.0|Brazil | B2: common-definitions | C2: AIM 3.0 | E2: ["Brazil"]
A3: AIM 3.0|Canada | B3: common-definitions | C3: AIM 3.0 | E3: ["Canada"]
A4: AIM 3.0|China | B4: common-definitions | C4: AIM 3.0 | E4: ["China", "Hong Kong"]
A5: AIM 3.0|EU & UK | B5: common-definitions | C5: AIM 3.0 | E5: ["Austria", "Belgium", "Cyprus", "Czechia", "Denmark", "Estonia", "Finland", "France", "Germany", "Greece", "Hungary", "Ireland", "Italy", "Latvia", "Lithuania", "Luxembourg", "Malta", "Netherlands", "Poland", "Portugal", "Slovakia", "Slovenia", "Spain", "Sweden", "United Kingdom"]
A6: AIM 3.0|Former USSR | B6: common-definitions | C6: AIM 3.0 | E6: ["Armenia", "Azerbaijan", "Belarus", "Georgia", "Kazakhstan", "Kyrgyzstan", "Moldova", "Russian Federation", "Tajikistan", "Turkmenistan", "Ukraine", "Uzbekistan"]
A7: AIM 3.0|India | B7: common-definitions | C7: AIM 3.0 | E7: ["India"]
A8: AIM 3.0|Japan | B8: common-definitions | C8: AIM 3.0 | E8: ["Japan"]
A9: AIM 3.0|Middle East | B9: common-definitions | C9: AIM 3.0 | E9: ["Bahrain", "Iran", "Iraq", "Israel", "Jordan", "Kuwait", "Lebanon", "Oman", "Qatar", "Saudi Arabia", "Syria", "United Arab Emirates", "Yemen"]
A10: AIM 3.0|New Zealand and Australia | B10: common-definitions | C10: AIM 3.0 | E10: ["Australia", "New Zealand"]
A11: AIM 3.0|North Africa | B11: common-definitions | C11: AIM 3.0 | E11: ["Algeria", "Egypt", "Libya", "Morocco", "Tunisia"]
A12: AIM 3.0|Other Africa | B12: common-definitions | C12: AIM 3.0 | E12: ["Angola", "Benin", "Botswana", "Burkina Faso", "Burundi", "Cabo Verde", "Cameroon", "Central African Republic", "Chad", "Comoros", "Congo", "C\u00f4te d'Ivoire", "Democratic Republic of the Congo", "Djibouti", "Equatorial Guinea", "Eritrea", "Eswatini", "Ethiopia", "Gabon", "Gambia", "Ghana", "Guinea", "Guinea-Bissau", "Kenya", "Lesotho", "Liberia", "Madagascar", "Malawi", "Mali", "Mauritania", "Mauritius", "Mayotte", "Mozambique", "Namibia", "Niger", "Nigeria", "Rwanda", "R\u00e9union", "Sao Tome and Principe", "Senegal", "Seychelles", "Sierra Leone", "Somalia", "South Africa", "Sudan", "Tanzania", "Togo", "Uganda", "Western Sahara", "Zambia", "Zimbabwe"]
A13: AIM 3.0|Rest of Asia | B13: common-definitions | C13: AIM 3.0 | E13: ["Afghanistan", "American Samoa", "Bangladesh", "Bhutan", "British Indian Ocean Territory", "Brunei Darussalam", "Christmas Island", "Cocos (Keeling) Islands", "Cook Islands", "Fiji", "French Polynesia", "French Southern Territories", "Guam", "Heard Island and McDonald Islands", "Kiribati", "Maldives", "Marshall Islands", "Micronesia", "Nauru", "Nepal", "New Caledonia", "Niue", "Norfolk Island", "Northern Mariana Islands", "Pakistan", "Palau", "Papua New Guinea", "Pitcairn", "Samoa", "Solomon Islands", "Sri Lanka", "Tokelau", "Tonga", "Tuvalu", "United States Minor Outlying Islands", "Vanuatu", "Wallis and Futuna"]
... A18: AIM 3.0|USA | B18: common-definitions | C18: AIM 3.0 | E18: ["United States"]
A19: AIM/Hub-Global 2.4|Brazil | B19: common-definitions | C19: AIM/Hub-Global 2.4
A20: AIM/Hub-Global 2.4|Canada | B20: common-definitions | C20: AIM/Hub-Global 2.4
A21: AIM/Hub-Global 2.4|China | B21: common-definitions | C21: AIM/Hub-Global 2.4
A22: AIM/Hub-Global 2.4|EU | B22: common-definitions | C22: AIM/Hub-Global 2.4
A23: AIM/Hub-Global 2.4|Former USSR | B23: common-definitions | C23: AIM/Hub-Global 2.4
A24: AIM/Hub-Global 2.4|India | B24: common-definitions | C24: AIM/Hub-Global 2.4
A25: AIM/Hub-Global 2.4|Japan | B25: common-definitions | C25: AIM/Hub-Global 2.4
A26: AIM/Hub-Global 2.4|Middle East | B26: common-definitions | C26: AIM/Hub-Global 2.4
A27: AIM/Hub-Global 2.4|New Zealand and Australia | B27: common-definitions | C27: AIM/Hub-Global 2.4
A28: AIM/Hub-Global 2.4|North Africa | B28: common-definitions | C28: AIM/Hub-Global 2.4
A29: AIM/Hub-Global 2.4|Other Africa | B29: common-definitions | C29: AIM/Hub-Global 2.4
A30: AIM/Hub-Global 2.4|Rest of Asia | B30: common-definitions | C30: AIM/Hub-Global 2.4
... A35: AIM/Hub-Global 2.4|USA | B35: common-definitions | C35: AIM/Hub-Global 2.4
A36: Africa (R10) | B36: common-definitions | C36: R10 | D36: Africa | E36: ["Algeria", "Angola", "Benin", "Botswana", "Burkina Faso", "Burundi", "Cameroon", "Cabo Verde", "Central African Republic", "Chad", "Comoros", "Congo", "C\u00f4te d'Ivoire", "Democratic Republic of the Congo", "Djibouti", "Egypt", "Equatorial Guinea", "Eritrea", "Ethiopia", "Gabon", "Gambia", "Ghana", "Guinea", "Guinea-Bissau", "Kenya", "Lesotho", "Liberia", "Libya", "Madagascar", "Malawi", "Mali", "Mauritania", "Mauritius", "Mayotte", "Morocco", "Mozambique", "Namibia", "Niger", "Nigeria", "Rwanda", "R\u00e9union", "Sao Tome and Principe", "Senegal", "Seychelles", "Sierra Leone", "Somalia", "South Africa", "South Sudan", "Sudan", "Eswatini", "Togo", "Tunisia", "Uganda", "Tanzania", "Western Sahara", "Zambia", "Zimbabwe"] | F36: R10AFRICA | I36: Depending on the spatial resolution, some models report Northern Africa as part of the Middle East region.
A37: African Union | B37: common-definitions | C37: G20 members
A38: Argentina | B38: common-definitions | C38: G20 members
A39: Asia (R5) | B39: common-definitions | C39: R5 | D39: The region includes Asian countries with the exception of the Middle East, Japan and Former Soviet Union states | E39: ["Afghanistan", "Bangladesh", "Bhutan", "Brunei Darussalam", "Cambodia", "China", "Cook Islands", "Fiji", "French Polynesia", "Hong Kong", "India", "Indonesia", "Kiribati", "Laos", "Macao", "Malaysia", "Maldives", "Marshall Islands", "Micronesia", "Mongolia", "Myanmar", "Nauru", "Nepal", "Niue", "New Caledonia", "North Korea", "Pakistan", "Papua New Guinea", "Palau", "Philippines", "South Korea", "Samoa", "Singapore", "Solomon Islands", "Sri Lanka", "Taiwan", "Thailand", "Timor-Leste", "Tonga", "Tuvalu", "Vanuatu", "Viet Nam"] | F39: R5ASIA | G39: R5.2ASIA
A40: Australia | B40: common-definitions | C40: G20 members
A41: Brazil | B41: common-definitions | C41: G20 members
A42: COFFEE 1.5|Africa (excluding South Africa) | B42: common-definitions | C42: COFFEE 1.5 | E42: ["Algeria", "Angola", "Benin", "Botswana", "Burkina Faso", "Burundi", "Cabo Verde", "Cameroon", "Central African Republic", "Chad", "Comoros", "Congo", "C\u00f4te d'Ivoire", "Democratic Republic of the Congo", "Djibouti", "Egypt", "Equatorial Guinea", "Eritrea", "Eswatini", "Ethiopia", "Gabon", "Gambia", "Ghana", "Guinea", "Guinea-Bissau", "Kenya", "Lesotho", "Liberia", "Libya", "Madagascar", "Malawi", "Mali", "Mauritania", "Mauritius", "Mayotte", "Morocco", "Mozambique", "Namibia", "Niger", "Nigeria", "Rwanda", "R\u00e9union", "Sao Tome and Principe", "Senegal", "Seychelles", "Sierra Leone", "Somalia", "South Sudan", "Sudan", "Tanzania", "Togo", "Tunisia", "Uganda", "Western Sahara", "Zambia"]
A43: COFFEE 1.5|Australia & New Zealand | B43: common-definitions | C43: COFFEE 1.5 | E43: ["Australia", "New Zealand"]
A44: COFFEE 1.5|Brazil | B44: common-definitions | C44: COFFEE 1.5 | E44: ["Brazil"]
A45: COFFEE 1.5|Canada | B45: common-definitions | C45: COFFEE 1.5 | E45: ["Canada", "Saint Helena, Ascension and Tristan da Cunha", "Saint Pierre and Miquelon"]
A46: COFFEE 1.5|Caspian Sea | B46: common-definitions | C46: COFFEE 1.5 | E46: ["Afghanistan", "Armenia", "Azerbaijan", "Georgia", "Kazakhstan", "Kyrgyzstan", "Pakistan", "Tajikistan", "Turkmenistan", "Uzbekistan"]
A47: COFFEE 1.5|Central America | B47: common-definitions | C47: COFFEE 1.5 | E47: ["Anguilla", "Antigua and Barbuda", "Aruba", "Bahamas", "Barbados", "Belize", "Bermuda", "Bonaire, Sint Eustatius and Saba", "Cayman Islands", "Costa Rica", "Cuba", "Cura\u00e7ao", "Dominica", "Dominican Republic", "El Salvador", "French Guiana", "Grenada", "Guadeloupe", "Guatemala", "Guyana", "Haiti", "Honduras", "Jamaica", "Martinique", "Mexico", "Montserrat", "Nicaragua", "Panama", "Saint Barth\u00e9lemy", "Saint Kitts and Nevis", "Saint Lucia", "Saint Martin (French part)", "Saint Vincent and the Grenadines", "Sint Maarten (Dutch part)", "Suriname", "Trinidad and Tobago", "Turks and Caicos Islands"]
A48: COFFEE 1.5|China | B48: common-definitions | C48: COFFEE 1.5 | E48: ["China", "Hong Kong", "Macao"]
A49: COFFEE 1.5|Europe | B49: common-definitions | C49: COFFEE 1.5 | E49: ["Andorra", "Austria", "Belgium", "Bouvet Island", "Bulgaria", "Cyprus", "Czechia", "Denmark", "Estonia", "Faroe Islands", "Finland", "France", "Germany", "Gibraltar", "Greece", "Greenland", "Guernsey", "Hungary", "Iceland", "Ireland", "Isle of Man", "Italy", "Jersey", "Latvia", "Liechtenstein", "Lithuania", "Luxembourg", "Malta", "Monaco", "Netherlands", "Norway", "Poland", "Portugal", "Romania", "San Marino", "Slovakia", "Slovenia", "Spain", "Svalbard and Jan Mayen", "Sweden", "Switzerland", "Turkey", "United Kingdom", "Vatican", "\u00c5land Islands"]
A50: COFFEE 1.5|India | B50: common-definitions | C50: COFFEE 1.5 | E50: ["India"]
A51: COFFEE 1.5|Japan | B51: common-definitions | C51: COFFEE 1.5 | E51: ["Japan"]
A52: COFFEE 1.5|Middle East | B52: common-definitions | C52: COFFEE 1.5 | E52: ["Bahrain", "Iran", "Iraq", "Israel", "Jordan", "Kuwait", "Lebanon", "Oman", "Palestine", "Qatar", "Saudi Arabia", "Syria", "United Arab Emirates", "Yemen"]
A53: COFFEE 1.5|Rest of Asia and Oceania | B53: common-definitions | C53: COFFEE 1.5 | E53: ["Antarctica", "Bangladesh", "Bhutan", "British Indian Ocean Territory", "Brunei Darussalam", "Cambodia", "Christmas Island", "Cocos (Keeling) Islands", "Cook Islands", "Fiji", "French Polynesia", "French Southern Territories", "Guam", "Heard Island and McDonald Islands", "Indonesia", "Kiribati", "Laos", "Malaysia", "Maldives", "Marshall Islands", "Micronesia", "Mongolia", "Myanmar", "Nauru", "Nepal", "New Caledonia", "Niue", "Norfolk Island", "North Korea", "Northern Mariana Islands", "Palau", "Papua New Guinea", "Philippines", "Pitcairn", "Samoa", "Singapore", "Solomon Islands", "Sri Lanka", "Taiwan", "Thailand", "Timor-Leste", "Tokelau", "Tonga", "Tuvalu", "Vanuatu", "Viet Nam", "Wallis and Futuna"]
... A59: COFFEE 1.5|United States | B59: common-definitions | C59: COFFEE 1.5 | E59: ["American Samoa", "British Virgin Islands", "Puerto Rico", "United States", "United States Minor Outlying Islands", "United States Virgin Islands"]
A60: Canada | B60: common-definitions | C60: G20 members
A61: China | B61: common-definitions | C61: G20 members
A62: China (R9) | B62: common-definitions | C62: R9 | D62: China | E62: ["China", "Hong Kong", "Macao"] | H62: R9CHINA
A63: China+ (R10) | B63: common-definitions | C63: R10 | D63: Eastern Asia, primarily China | E63: ["China", "Hong Kong", "Macao", "Mongolia", "North Korea", "South Korea"] | F63: R10CHINA+
A64: Europe (R10) | B64: common-definitions | C64: R10 | D64: Europe (including Turkey) | E64: ["Albania", "Austria", "Belgium", "Bosnia and Herzegovina", "Bulgaria", "Croatia", "Cyprus", "Czechia", "Denmark", "Estonia", "France", "Finland", "Germany", "Greece", "Hungary", "Iceland", "Ireland", "Italy", "Kosovo", "Latvia", "Lithuania", "Luxembourg", "Malta", "Montenegro", "Netherlands", "North Macedonia", "Norway", "Portugal", "Switzerland", "Poland", "Romania", "Serbia", "Slovakia", "Slovenia", "Spain", "Sweden", "Turkey", "United Kingdom"] | F64: R10EUROPE
A65: European Union | B65: common-definitions | C65: G20 members
A66: European Union (R9) | B66: common-definitions | C66: R9 | D66: European Union (membership status 2023) | E66: ["Austria", "Belgium", "Bulgaria", "Croatia", "Cyprus", "Czechia", "Denmark", "Estonia", "Finland", "France", "Germany", "Greece", "Hungary", "Ireland", "Italy", "Latvia", "Lithuania", "Luxembourg", "Malta", "Netherlands", "Poland", "Portugal", "Romania", "Slovakia", "Slovenia", "Spain", "Sweden"] | H66: R9EU | I66: Depending on the spatial resolution, reporting by some models may differ from the current list of EU27 members (2023).
A67: European Union and United Kingdom | B67: common-definitions | C67: G20 members | I67: This region is used for models that do not have a distinct regional resolution for the United Kingdom and the European Union.
A68: France | B68: common-definitions | C68: G20 members
A69: GCAM 7.1|Africa_Eastern | B69: common-definitions | C69: GCAM 7.1 | E69: ["Burundi", "Comoros", "Djibouti", "Eritrea", "Ethiopia", "Kenya", "Madagascar", "Mauritius", "R\u00e9union", "Rwanda", "Somalia", "Sudan", "South Sudan", "Uganda"]
A70: GCAM 7.1|Africa_Northern | B70: common-definitions | C70: GCAM 7.1 | E70: ["Algeria", "Egypt", "Libya", "Morocco", "Tunisia", "Western Sahara"]
A71: GCAM 7.1|Africa_Southern | B71: common-definitions | C71: GCAM 7.1 | E71: ["Angola", "Mozambique", "Malawi", "Lesotho", "Botswana", "Tanzania", "Namibia", "Eswatini", "Zambia", "Zimbabwe"]
A72: GCAM 7.1|Africa_Western | B72: common-definitions | C72: GCAM 7.1 | E72: ["Benin", "Congo", "Democratic Republic of the Congo", "Cameroon", "Chad", "Central African Republic", "Cabo Verde", "Equatorial Guinea", "Gambia", "Gabon", "Ghana", "Guinea", "C\u00f4te d'Ivoire", "Liberia", "Mali", "Mauritania", "Niger", "Nigeria", "Guinea-Bissau", "Senegal", "Sierra Leone", "Togo", "Sao Tome and Principe", "Burkina Faso"]
A73: GCAM 7.1|Argentina | B73: common-definitions | C73: GCAM 7.1 | E73: ["Argentina"]
A74: GCAM 7.1|Australia_NZ | B74: common-definitions | C74: GCAM 7.1 | E74: ["Australia", "New Zealand"]
A75: GCAM 7.1|Brazil | B75: common-definitions | C75: GCAM 7.1 | E75: ["Brazil"]
A76: GCAM 7.1|Canada | B76: common-definitions | C76: GCAM 7.1 | E76: ["Canada"]
A77: GCAM 7.1|Central America and Caribbean | B77: common-definitions | C77: GCAM 7.1 | E77: ["Antigua and Barbuda", "Barbados", "Bermuda", "Bahamas", "Belize", "Cayman Islands", "Costa Rica", "Cuba", "Dominica", "Dominican Republic", "El Salvador", "Grenada", "Guatemala", "Haiti", "Honduras", "Jamaica", "Martinique", "Montserrat", "Aruba", "Anguilla", "Nicaragua", "Panama", "Saint Kitts and Nevis", "Saint Lucia", "Trinidad and Tobago", "Saint Vincent and the Grenadines", "Guadeloupe"]
A78: GCAM 7.1|Central Asia | B78: common-definitions | C78: GCAM 7.1 | E78: ["Azerbaijan", "Armenia", "Georgia", "Kyrgyzstan", "Kazakhstan", "Mongolia", "Tajikistan", "Turkmenistan", "Uzbekistan"]
A79: GCAM 7.1|China | B79: common-definitions | C79: GCAM 7.1 | E79: ["China", "Hong Kong", "Macao"]
A80: GCAM 7.1|Colombia | B80: common-definitions | C80: GCAM 7.1 | E80: ["Colombia"]
... A100: GCAM 7.1|USA | B100: common-definitions | C100: GCAM 7.1 | E100: ["Puerto Rico", "United States", "United States Virgin Islands"]
A101: Germany | B101: common-definitions | C101: G20 members
A102: IMACLIM 2.0|Africa | B102: common-definitions | C102: IMACLIM 2.0
A103: IMACLIM 2.0|Brazil | B103: common-definitions | C103: IMACLIM 2.0
A104: IMACLIM 2.0|Canada | B104: common-definitions | C104: IMACLIM 2.0
A105: IMACLIM 2.0|China | B105: common-definitions | C105: IMACLIM 2.0
A106: IMACLIM 2.0|Europe excluding FSU | B106: common-definitions | C106: IMACLIM 2.0
A107: IMACLIM 2.0|Former Soviet Union excluding EU Baltic countries | B107: common-definitions | C107: IMACLIM 2.0
A108: IMACLIM 2.0|India | B108: common-definitions | C108: IMACLIM 2.0
A109: IMACLIM 2.0|Japan, Australia, New Zealand and Korea | B109: common-definitions | C109: IMACLIM 2.0
A110: IMACLIM 2.0|Middle East | B110: common-definitions | C110: IMACLIM 2.0
A111: IMACLIM 2.0|Rest of Asia | B111: common-definitions | C111: IMACLIM 2.0
A112: IMACLIM 2.0|Rest of Latin America | B112: common-definitions | C112: IMACLIM 2.0
A113: IMACLIM 2.0|USA | B113: common-definitions | C113: IMACLIM 2.0
A114: IMAGE 3.4|Brazil | B114: common-definitions | C114: IMAGE 3.4 | E114: ["Brazil"]
A115: IMAGE 3.4|Canada | B115: common-definitions | C115: IMAGE 3.4 | E115: ["Canada"]
A116: IMAGE 3.4|Central America | B116: common-definitions | C116: IMAGE 3.4 | E116: ["Anguilla", "Aruba", "Bahamas", "Barbados", "Belize", "Bermuda", "Cayman Islands", "Costa Rica", "Dominica", "Dominican Republic", "El Salvador", "Grenada", "Guadeloupe", "Guatemala", "Haiti", "Honduras", "Jamaica", "Martinique", "Montserrat", "Nicaragua", "Panama", "Puerto Rico", "Saint Kitts and Nevis", "Saint Lucia", "Saint Vincent and the Grenadines", "Trinidad and Tobago", "Turks and Caicos Islands", "British Virgin Islands", "United States Virgin Islands"]
A117: IMAGE 3.4|Central Asia | B117: common-definitions | C117: IMAGE 3.4 | E117: ["Kazakhstan", "Kyrgyzstan", "Tajikistan", "Turkmenistan", "Uzbekistan"]
A118: IMAGE 3.4|Central Europe | B118: common-definitions | C118: IMAGE 3.4 | E118: ["Albania", "Bosnia and Herzegovina", "Bulgaria", "Croatia", "Cyprus", "Czechia", "Estonia", "Hungary", "Latvia", "Lithuania", "North Macedonia", "Poland", "Romania", "Serbia", "Montenegro", "Slovakia", "Slovenia"]
A119: IMAGE 3.4|China Region | B119: common-definitions | C119: IMAGE 3.4 | E119: ["China", "Hong Kong", "Macao", "Mongolia", "Taiwan"]
A120: IMAGE 3.4|Eastern Africa | B120: common-definitions | C120: IMAGE 3.4 | E120: ["Burundi", "Comoros", "Djibouti", "Eritrea", "Ethiopia", "Kenya", "Madagascar", "Mauritius", "R\u00e9union", "Rwanda", "Seychelles", "Somalia", "Sudan", "Uganda"]
A121: IMAGE 3.4|India | B121: common-definitions | C121: IMAGE 3.4 | E121: ["India"]
A122: IMAGE 3.4|Indonesia Region | B122: common-definitions | C122: IMAGE 3.4 | E122: ["Timor-Leste", "Indonesia", "Papua New Guinea"]
A123: IMAGE 3.4|Japan | B123: common-definitions | C123: IMAGE 3.4 | E123: ["Japan"]
A124: IMAGE 3.4|Korea Region | B124: common-definitions | C124: IMAGE 3.4 | E124: ["South Korea", "North Korea"]
A125: IMAGE 3.4|Mexico | B125: common-definitions | C125: IMAGE 3.4 | E125: ["Mexico"]
... A139: IMAGE 3.4|Western Europe | B139: common-definitions | C139: IMAGE 3.4 | E139: ["Andorra", "Austria", "Belgium", "Denmark", "Faroe Islands", "Finland", "France", "Germany", "Gibraltar", "Greece", "Iceland", "Ireland", "Italy", "Liechtenstein", "Luxembourg", "Malta", "Monaco", "Netherlands", "Norway", "Portugal", "San Marino", "Spain", "Sweden", "Switzerland", "United Kingdom", "Vatican"]
A140: India | B140: common-definitions | C140: G20 members
A141: India (R9) | B141: common-definitions | C141: R9 | D141: India | E141: ["India"] | H141: R9INDIA
A142: India+ (R10) | B142: common-definitions | C142: R10 | D142: South Asia, primarily India | E142: ["India", "Afghanistan", "Bangladesh", "Bhutan", "Maldives", "Nepal", "Pakistan", "Sri Lanka"] | F142: R10INDIA+
A143: Indonesia | B143: common-definitions | C143: G20 members
A144: International | B144: common-definitions | C144: common | D144: This region should be used if data cannot be assigned to a specific region, e.g., emissions from bunker fuels in aviation or shipping
A145: Italy | B145: common-definitions | C145: G20 members
...

Sheet variable
A1: variable | B1: description | C1: repository | D1: unit | E1: tier | F1: weight | G1: notes | H1: navigate | I1: range | J1: sdg | K1: min | L1: lower_bound | M1: drop_negative_weights | N1: engage | O1: shape | P1: skip-region-aggregation | Q1: agmip | R1: components
A2: Agricultural Demand | B2: Total demand for food, non-food and feed products (crops and livestock) and bioenergy crops (1st & 2nd generation) | C2: common-definitions | D2: million t DM/yr | E2: 1 | Q2: Domestic use (CONS)
A3: Agricultural Demand|Crops | B3: Demand for crops including food, feed products and bioenergy (1st & 2nd generation crops) | C3: common-definitions | D3: million t DM/yr | E3: 1 | Q3: Domestic use (CONS) - Crops (CRP)
A4: Agricultural Demand|Crops|Bioenergy | B4: Demand for bioenergy crops (1st & 2nd generation) | C4: common-definitions | D4: million t DM/yr | E4: 1
A5: Agricultural Demand|Crops|Bioenergy|1st Generation | B5: Demand for 1st generation bioenergy crops (sugar, starch and oil crops) | C5: common-definitions | D5: million t DM/yr | E5: 2
A6: Agricultural Demand|Crops|Bioenergy|2nd generation | B6: Demand for second-generation bioenergy crops (short rotation grasses, short rotation trees) | C6: common-definitions | D6: million t DM/yr | E6: 1 | Q6: Domestic use (CONS) - Energy Crops (ECP)
A7: Agricultural Demand|Crops|Feed | B7: Demand for feed crops | C7: common-definitions | D7: million t DM/yr | E7: 2 | Q7: Feed demand (FEED) - Crops (CRP)
A8: Agricultural Demand|Crops|Feed|Cereals | B8: Demand for feed crops - cereals (maize, rice, temperate cereals and tropical cereals) | C8: common-definitions | D8: million t DM/yr | E8: 3
A9: Agricultural Demand|Crops|Feed|Oil Crops | B9: Demand for feed crops - oil crops (cotton seed, groundnuts, oilpalms, other oil crops incl rapeseed, soybean, sunflower) | C9: common-definitions | D9: million t DM/yr | E9: 3
A10: Agricultural Demand|Crops|Feed|Other Crops | B10: Demand for feed crops - other crops (fruits, vegetables, nuts, potatoes, pulses, tropical roots) | C10: common-definitions | D10: million t DM/yr | E10: 3
A11: Agricultural Demand|Crops|Feed|Sugar Crops | B11: Demand for feed crops - sugar crops (sugar beet, sugar cane) | C11: common-definitions | D11: million t DM/yr | E11: 3
A12: Agricultural Demand|Crops|Food | B12: Demand for food crops | C12: common-definitions | D12: million t DM/yr | E12: 2 | Q12: Food demand (FOOD) - Crops (CRP)
A13: Agricultural Demand|Crops|Food|Cereals | B13: Demand for food crops - cereals (maize, rice, temperate cereals and tropical cereals) | C13: common-definitions | D13: million t DM/yr | E13: 3
A14: Agricultural Demand|Crops|Food|Oil Crops | B14: Demand for food crops - oil crops (cotton seed, groundnuts, oilpalms, other oil crops incl rapeseed, soybean, sunflower) | C14: common-definitions | D14: million t DM/yr | E14: 3
A15: Agricultural Demand|Crops|Food|Other Crops | B15: Demand for food crops - other crops (fruits, vegetables, nuts, potatoes, pulses, tropical roots) | C15: common-definitions | D15: million t DM/yr | E15: 3
A16: Agricultural Demand|Crops|Food|Sugar Crops | B16: Demand for food crops - sugar crops (sugar beet, sugar cane) | C16: common-definitions | D16: million t DM/yr | E16: 3
A17: Agricultural Demand|Crops|Other | B17: Demand for crops for other uses | C17: common-definitions | D17: million t DM/yr | E17: 2
A18: Agricultural Demand|Livestock | B18: Demand for livestock products (excluding fish) | C18: common-definitions | D18: million t DM/yr | E18: 1 | Q18: Domestic use (CONS) - LSP
A19: Agricultural Demand|Livestock|Feed | B19: Demand for livestock products used as feed (excluding fish) | C19: common-definitions | D19: million t DM/yr | E19: 2
A20: Agricultural Demand|Livestock|Food | B20: Demand for livestock products used as food (excluding fish) | C20: common-definitions | D20: million t DM/yr | E20: 2 | Q20: Food demand (FOOD) - Livestock (LSP)
A21: Agricultural Demand|Livestock|Food|Dairy | B21: Demand for livestock products used as food - dairy products (milk, eggs) | C21: common-definitions | D21: million t DM/yr | E21: 3
A22: Agricultural Demand|Livestock|Food|Non-Ruminant | B22: Demand for livestock products used as food - monogastric meat (pig, poultry) | C22: common-definitions | D22: million t DM/yr | E22: 3
A23: Agricultural Demand|Livestock|Food|Ruminant | B23: Demand for livestock products used as food - ruminant meat (cattle, goat, sheep) | C23: common-definitions | D23: million t DM/yr | E23: 3
A24: Agricultural Demand|Livestock|Other | B24: Demand for livestock products for other uses | C24: common-definitions | D24: million t DM/yr | E24: 2
A25: Agricultural Demand|Residues | B25: Demand for residues from agricultural production for feed, bioenergy and other uses | C25: common-definitions | D25: million t DM/yr | E25: 2
A26: Agricultural Demand|Residues|Bioenergy | B26: Demand for residues as bioenergy | C26: common-definitions | D26: million t DM/yr | E26: 2
A27: Agricultural Demand|Residues|Feed | B27: Demand for residues as feed | C27: common-definitions | D27: million t DM/yr | E27: 2
A28: Agricultural Demand|Residues|Other | B28: Demand of residues for other uses | C28: common-definitions | D28: million t DM/yr | E28: 2
A29: Agricultural Material Footprint [per capita] | B29: Biomass usage per capita excluding pasture and forestry | C29: common-definitions | D29: tDM/cap/yr | F29: Population | J29: 12 | O29: Agricultural Material Footprint
A30: Agricultural Production | B30: Total production of food, non-food and feed products (crops and livestock) and bioenergy crops (1st & 2nd generation) | C30: common-definitions | D30: million t DM/yr | E30: 1 | Q30: Production (PROD)
A31: Agricultural Production|Crops | B31: Production of crops | C31: common-definitions | D31: million t DM/yr | E31: 1 | Q31: Production (PROD) - All crops (CRP)
A32: Agricultural Production|Crops|Cereals | B32: Production of cereals (maize, rice, temperate cereals and tropical cereals) | C32: common-definitions | D32: million t DM/yr | E32: 2
A33: Agricultural Production|Crops|Energy Crops | B33: Production of second-generation bioenergy crops (short rotation grasses, short rotation trees) | C33: common-definitions | D33: million t DM/yr | E33: 2
A34: Agricultural Production|Crops|Oil Crops | B34: Production of oil crops (cotton seed, groundnuts, oilpalms, other oil crops incl rapeseed, soybean, sunflower) | C34: common-definitions | D34: million t DM/yr | E34: 2
A35: Agricultural Production|Crops|Other Crops | B35: Production of other crops (fruits, vegetables, nuts, potatoes, pulses, tropical roots) | C35: common-definitions | D35: million t DM/yr | E35: 2
A36: Agricultural Production|Crops|Sugar Crops | B36: Production of sugar crops (sugar beet, sugar cane) | C36: common-definitions | D36: million t DM/yr | E36: 2
A37: Agricultural Production|Livestock | B37: Production of livestock products (excluding fish) | C37: common-definitions | D37: million t DM/yr | E37: 1 | Q37: Production (PROD) - Livestock (LSP)
A38: Agricultural Production|Livestock|Dairy | B38: Production of dairy products (milk, eggs) | C38: common-definitions | D38: million t DM/yr | E38: 2 | Q38: Production (PROD) - Dairy (DRY)
A39: Agricultural Production|Livestock|Non-Ruminant | B39: Production of monogastric meat (pig, poultry) | C39: common-definitions | D39: million t DM/yr | E39: 2 | Q39: Production (PROD) - Dairy (DRY)
A40: Agricultural Production|Livestock|Ruminant | B40: Production of ruminant meat (cattle, goat, sheep) | C40: common-definitions | D40: million t DM/yr | E40: 2 | Q40: Production (PROD) - Dairy (DRY)
A41: Agricultural Production|Residues | B41: Production of agricultural residues | C41: common-definitions | D41: million t DM/yr | E41: 2
A42: Air Pollution|PM2.5|Urban Population | B42: Urban population weighted annual average PM2.5 concentrations. | C42: common-definitions | D42: ug/m3 | F42: Population|Urban | J42: 11 | O42: Air Pollution|PM2.5|Urban population
A43: Capacity Additions|Electricity | B43: Total annual new installation of electricity generation capacity | C43: common-definitions | D43: GW/yr | E43: 2 | G43: This variable should be computed as yearly average additions between the previous and the current reported time step.
A44: Capacity Additions|Electricity|Ammonia | B44: Annual new installation of capacity to generate electricity from ammonia | C44: common-definitions | D44: GW/yr | E44: 2 | G44: This variable should be computed as yearly average additions between the previous and the current reported time step.
A45: Capacity Additions|Electricity|Biomass | B45: Annual new installation of capacity to generate electricity from purpose-grown bioenergy crops, biogas, crop and forestry residue, municipal solid waste bioenergy and traditional biomass | C45: common-definitions | D45: GW/yr | E45: 2 | G45: This variable should be computed as yearly average additions between the previous and the current reported time step.
A46: Capacity Additions|Electricity|Biomass|w/ CCS | B46: Annual new installation of capacity to generate electricity from purpose-grown bioenergy crops, biogas, crop and forestry residue, municipal solid waste bioenergy and traditional biomass in combination with carbon capture and storage (CCS) | C46: common-definitions | D46: GW/yr | E46: 2 | G46: This variable should be computed as yearly average additions between the previous and the current reported time step.
A47: Capacity Additions|Electricity|Biomass|w/o CCS | B47: Annual new installation of capacity to generate electricity from purpose-grown bioenergy crops, biogas, crop and forestry residue, municipal solid waste bioenergy and traditional biomass without carbon capture and storage (CCS) | C47: common-definitions | D47: GW/yr | E47: 2 | G47: This variable should be computed as yearly average additions between the previous and the current reported time step.
A48: Capacity Additions|Electricity|Coal | B48: Annual new installation of capacity to generate electricity from coal including lignite | C48: common-definitions | D48: GW/yr | E48: 2 | G48: This variable should be computed as yearly average additions between the previous and the current reported time step.
A49: Capacity Additions|Electricity|Coal|w/ CCS | B49: Annual new installation of capacity to generate electricity from coal including lignite in combination with carbon capture and storage (CCS) | C49: common-definitions | D49: GW/yr | E49: 2 | G49: This variable should be computed as yearly average additions between the previous and the current reported time step.
A50: Capacity Additions|Electricity|Coal|w/o CCS | B50: Annual new installation of capacity to generate electricity from coal including lignite without carbon capture and storage (CCS) | C50: common-definitions | D50: GW/yr | E50: 2 | G50: This variable should be computed as yearly average additions between the previous and the current reported time step.
A51: Capacity Additions|Electricity|Fossil | B51: Annual new installation of capacity to generate electricity from fossil fuels including coal, natural gas and conventional/unconventional oil | C51: common-definitions | D51: GW/yr | E51: 2 | G51: This variable should be computed as yearly average additions between the previous and the current reported time step.
A52: Capacity Additions|Electricity|Fossil|w/ CCS | B52: Annual new installation of capacity to generate electricity from fossil fuels including coal, natural gas and conventional/unconventional oil in combination with carbon capture and storage (CCS) | C52: common-definitions | D52: GW/yr | E52: 2 | G52: This variable should be computed as yearly average additions between the previous and the current reported time step.
A53: Capacity Additions|Electricity|Fossil|w/o CCS | B53: Annual new installation of capacity to generate electricity from fossil fuels including coal, natural gas and conventional/unconventional oil without carbon capture and storage (CCS) | C53: common-definitions | D53: GW/yr | E53: 2 | G53: This variable should be computed as yearly average additions between the previous and the current reported time step.
A54: Capacity Additions|Electricity|Gas | B54: Annual new installation of capacity to generate electricity from natural gas (fossil methane) | C54: common-definitions | D54: GW/yr | E54: 2 | G54: This variable should be computed as yearly average additions between the previous and the current reported time step.
... A120: Capacity Additions|Solids|Coal | B120: Total annual new capacity installation to produce coal, lignite, and derived products (e.g., coke, briquettes) | C120: common-definitions | D120: GW/yr | E120: 3 | G120: This variable should be computed as yearly average additions between the previous and the current reported time step.
A121: Capacity|Electricity | B121: Total installed (available) electricity generation capacity | C121: common-definitions | D121: GW | E121: 1
A122: Capacity|Electricity|Ammonia | B122: Installed (available) capacity to generate electricity from ammonia | C122: common-definitions | D122: GW | E122: 1
A123: Capacity|Electricity|Biomass | B123: Installed (available) capacity to generate electricity from purpose-grown bioenergy crops, biogas, crop and forestry residue, municipal solid waste bioenergy and traditional biomass | C123: common-definitions | D123: GW | E123: 1
A124: Capacity|Electricity|Biomass|w/ CCS | B124: Installed (available) capacity to generate electricity from purpose-grown bioenergy crops, biogas, crop and forestry residue, municipal solid waste bioenergy and traditional biomass in combination with carbon capture and storage (CCS) | C124: common-definitions | D124: GW | E124: 1
A125: Capacity|Electricity|Biomass|w/o CCS | B125: Installed (available) capacity to generate electricity from purpose-grown bioenergy crops, biogas, crop and forestry residue, municipal solid waste bioenergy and traditional biomass without carbon capture and storage (CCS) | C125: common-definitions | D125: GW | E125: 1
A126: Capacity|Electricity|Coal | B126: Installed (available) capacity to generate electricity from coal including lignite | C126: common-definitions | D126: GW | E126: 1
A127: Capacity|Electricity|Coal|w/ CCS | B127: Installed (available) capacity to generate electricity from coal including lignite in combination with carbon capture and storage (CCS) | C127: common-definitions | D127: GW | E127: 1
A128: Capacity|Electricity|Coal|w/o CCS | B128: Installed (available) capacity to generate electricity from coal including lignite without carbon capture and storage (CCS) | C128: common-definitions | D128: GW | E128: 1
A129: Capacity|Electricity|Fossil | B129: Installed (available) capacity to generate electricity from fossil fuels including coal, natural gas and conventional/unconventional oil | C129: common-definitions | D129: GW | E129: 1
A130: Capacity|Electricity|Fossil|w/ CCS | B130: Installed (available) capacity to generate electricity from fossil fuels including coal, natural gas and conventional/unconventional oil in combination with carbon capture and storage (CCS) | C130: common-definitions | D130: GW | E130: 1
A131: Capacity|Electricity|Fossil|w/o CCS | B131: Installed (available) capacity to generate electricity from fossil fuels including coal, natural gas and conventional/unconventional oil without carbon capture and storage (CCS) | C131: common-definitions | D131: GW | E131: 1
A132: Capacity|Electricity|Gas | B132: Installed (available) capacity to generate electricity from natural gas (fossil methane) | C132: common-definitions | D132: GW | E132: 1
... A352: Capital Cost|Electricity|Wind|Onshore|* | B352: Capital cost of a newly installed plant to generate electricity from onshore wind power for a specific technology | C352: common-definitions | D352: USD_2010/kW | E352: 2
A353: Capital Cost|Gases | B353: Capital cost of a newly installed plant to produce gaseous fuels including natural gas and biogas, not including hydrogen | C353: common-definitions | D353: USD_2010/kW
A354: Capital Cost|Gases|* | B354: Capital cost of a newly installed plant to produce gaseous fuels including natural gas and biogas, not including hydrogen for a specific technology | C354: common-definitions | D354: USD_2010/kW
A355: Capital Cost|Gases|Biomass | B355: Capital cost of a newly installed plant to produce gas from biogenic sources, mainly biogas | C355: common-definitions | D355: USD_2010/kW
A356: Capital Cost|Gases|Biomass|* | B356: Capital cost of a newly installed plant to produce gas from biogenic sources, mainly biogas for a specific technology | C356: common-definitions | D356: USD_2010/kW
A357: Capital Cost|Gases|Coal | B357: Capital cost of a newly installed plant to produce gaseous fuels from coal gasification | C357: common-definitions | D357: USD_2010/kW
A358: Capital Cost|Gases|Coal|* | B358: Capital cost of a newly installed plant to produce gaseous fuels from coal gasification for a specific technology | C358: common-definitions | D358: USD_2010/kW
A359: Capital Cost|Gases|Electricity | B359: Capital cost of a newly installed plant to produce gas from electricity i.e., 'power-to-gas' (if hydrogen is not explicitly modeled as an intermediate product) | C359: common-definitions | D359: USD_2010/kW
A360: Capital Cost|Gases|Electricity|* | B360: Capital cost of a newly installed plant to produce gas from electricity i.e., 'power-to-gas' (if hydrogen is not explicitly modeled as an intermediate product) for a specific technology | C360: common-definitions | D360: USD_2010/kW
A361: Capital Cost|Gases|Fossil | B361: Capital cost of a newly installed plant to produce gaseous fuels from fossil fuels including natural gas and coal | C361: common-definitions | D361: USD_2010/kW
A362: Capital Cost|Gases|Fossil|* | B362: Capital cost of a newly installed plant to produce gaseous fuels from fossil fuels including natural gas and coal for a specific technology | C362: common-definitions | D362: USD_2010/kW
A363: Capital Cost|Gases|Gas | B363: Capital cost of a newly installed plant to produce fossil methane ('natural gas') | C363: common-definitions | D363: USD_2010/kW
A364: Capital Cost|Gases|Gas|* | B364: Capital cost of a newly installed plant to produce fossil methane ('natural gas') for a specific technology | C364: common-definitions | D364: USD_2010/kW
... A500: Capital Cost|Solids|Coal|* | B500: Capital cost of a newly installed plant to produce coal, lignite, and derived products (e.g., coke, briquettes) for a specific technology | C500: common-definitions | D500: USD_2010/kW
A501: Capital Formation | B501: Net additions to the physical capital stock | C501: common-definitions | D501: billion USD_2010/yr | E501: 1
A502: Capital Stock | B502: Macroeconomic capital stock | C502: common-definitions | D502: billion USD_2010/yr
A503: Carbon Capture | B503: Total amount of carbon dioxide (CO2) captured either from the atmosphere, directly from oceans, or from point sources as energy use in supply and demand sectors (IPCC category 1A, 1B) or industrial processes (IPCC categories 2A, B, C, E) | C503: common-definitions | D503: Mt CO2/yr | E503: 1 | L503: 0 | R503: ["Carbon Capture|Geological Storage", "Carbon Capture|Other Storage", "Carbon Capture|Leakage", "Carbon Capture|Utilization"]
A504: Carbon Capture|Direct Air Capture | B504: Captured carbon dioxide (CO2) from direct air capture | C504: common-definitions | D504: Mt CO2/yr | E504: 1 | G504: Values should be reported as positive numbers. | L504: 0
A505: Carbon Capture|Direct Ocean Capture | B505: Captured carbon dioxide (CO2) from direct ocean capture | C505: common-definitions | D505: Mt CO2/yr | E505: 1 | G505: Values should be reported as positive numbers. | L505: 0
A506: Carbon Capture|Energy | B506: Captured carbon dioxide (CO2) from energy use in supply and demand sectors (IPCC category 1A, 1B) | C506: common-definitions | D506: Mt CO2/yr | E506: 1 | G506: Values should be reported as positive numbers. | L506: 0
A507: Carbon Capture|Energy|Biomass | B507: Captured carbon dioxide (CO2) from purpose-grown bioenergy crops, biogas, crop and forestry residue, municipal solid waste bioenergy and traditional biomass in supply and demand sectors (IPCC category 1A, 1B) | C507: common-definitions | D507: Mt CO2/yr | E507: 1 | G507: Values should be reported as positive numbers. | H507: Carbon Capture|Biomass | L507: 0 | N507: Carbon Capture|Biomass
A508: Carbon Capture|Energy|Demand | B508: Captured carbon dioxide (CO2) during energy consumption | C508: common-definitions | D508: Mt CO2/yr | E508: 2 | G508: Values should be reported as positive numbers. | L508: 0
A509: Carbon Capture|Energy|Demand|Biomass | B509: Captured carbon dioxide (CO2) during direct consumption of purpose-grown bioenergy crops, biogas, crop and forestry residue, municipal solid waste bioenergy and traditional biomass | C509: common-definitions | D509: Mt CO2/yr | E509: 2 | G509: Values should be reported as positive numbers. | L509: 0
A510: Carbon Capture|Energy|Demand|Fossil | B510: Captured carbon dioxide (CO2) during direct consumption of fossil fuels including coal, natural gas and conventional/unconventional oil | C510: common-definitions | D510: Mt CO2/yr | E510: 2 | G510: Values should be reported as positive numbers. | L510: 0
A511: Carbon Capture|Energy|Demand|Industry | B511: Captured carbon dioxide (CO2) during energy consumption in industry | C511: common-definitions | D511: Mt CO2/yr | E511: 2 | G511: Values should be reported as positive numbers. | H511: Carbon Capture|Industry | L511: 0
A512: Carbon Capture|Energy|Demand|Industry|Biomass | B512: Captured carbon dioxide (CO2) during use of purpose-grown bioenergy crops, biogas, crop and forestry residue, municipal solid waste bioenergy and traditional biomass in industry | C512: common-definitions | D512: Mt CO2/yr | E512: 2 | G512: Values should be reported as positive numbers. | H512: Carbon Capture|Industry|Biomass | L512: 0 | N512: Carbon Capture|Industry|Biomass
A513: Carbon Capture|Energy|Demand|Industry|Chemicals | B513: Captured carbon dioxide (CO2) during energy consumption in production of chemicals | C513: common-definitions | D513: Mt CO2/yr | E513: 2 | G513: Values should be reported as positive numbers. | H513: Carbon Capture|Industry|Chemicals | L513: 0
A514: Carbon Capture|Energy|Demand|Industry|Chemicals|Biomass | B514: Captured carbon dioxide (CO2) during use of purpose-grown bioenergy crops, biogas, crop and forestry residue, municipal solid waste bioenergy and traditional biomass in production of chemicals | C514: common-definitions | D514: Mt CO2/yr | E514: 2 | G514: Values should be reported as positive numbers. | H514: Carbon Capture|Industry|Biomass|Chemicals | L514: 0
A515: Carbon Capture|Energy|Demand|Industry|Chemicals|Fossil | B515: Captured carbon dioxide (CO2) during use of fossil fuels including coal, natural gas and conventional/unconventional oil in production of chemicals | C515: common-definitions | D515: Mt CO2/yr | E515: 2 | G515: Values should be reported as positive numbers. | H515: Carbon Capture|Industry|Fossil|Chemicals | L515: 0
A516: Carbon Capture|Energy|Demand|Industry|Chemicals|Synthetic Fuels | B516: Captured carbon dioxide (CO2) during use of synthetic fuels produced from carbon captured from fossil fuels and directly or indirectly from the atmosphere, e.g. using carbon-capture- and-utilization (CCU) from biomass or fossil fuels or Direct Air Capture (DAC) in production of chemicals | C516: common-definitions | D516: Mt CO2/yr | E516: 2 | G516: Values should be reported as positive numbers. | H516: Carbon Capture|Industry|Electricity|Chemicals | L516: 0
A517: Carbon Capture|Energy|Demand|Industry|Chemicals|Synthetic Fuels|Carbon-Neutral | B517: Captured carbon dioxide (CO2) during use of synthetic fuels produced from carbon captured directly or indirectly from the atmosphere, e.g. using carbon-capture-and-utilization (CCU) from biomass or Direct Air Capture (DAC), not derived from fossil fuels in production of chemicals | C517: common-definitions | D517: Mt CO2/yr | E517: 2 | G517: Values should be reported as positive numbers. | H517: Carbon Capture|Industry|Synthetic Fuels|Carbon-Neutral|Chemicals | L517: 0
A518: Carbon Capture|Energy|Demand|Industry|Chemicals|Synthetic Fuels|Fossil | B518: Captured carbon dioxide (CO2) during use of synthetic fuels produced from carbon-capture-and-utilization (CCU) of fossil fuels in production of chemicals | C518: common-definitions | D518: Mt CO2/yr | E518: 2 | G518: Values should be reported as positive numbers. | H518: Carbon Capture|Industry|Synthetic Fuels|Fossil|Chemicals | L518: 0
A519: Carbon Capture|Energy|Demand|Industry|Chemicals|Synthetic Fuels|Industrial Processes | B519: Captured carbon dioxide (CO2) during use of synthetic fuels produced from carbon-capture-and-utilization (CCU) of industrial processes in production of chemicals | C519: common-definitions | D519: Mt CO2/yr | E519: 2 | G519: Values should be reported as positive numbers. | H519: Carbon Capture|Industry|Synthetic Fuels|Industrial Processes|Chemicals | L519: 0
...

Sheet scenario
A1: scenario | B1: description
A2: SSP1 - High Emissions | B2: 'Sustainability – Taking the Green Road' (SSP1) combined with 'High Emissions' climate policy assumptions following the ScenarioMIP protocol
A3: SSP1 - High Emissions_a | B3: 'Sustainability – Taking the Green Road' (SSP1) combined with 'High Emissions' Option a climate policy assumptions following the ScenarioMIP protocol
A4: SSP1 - High Emissions_b | B4: 'Sustainability – Taking the Green Road' (SSP1) combined with 'High Emissions' Option b climate policy assumptions following the ScenarioMIP protocol
A5: SSP1 - High Emissions_c | B5: 'Sustainability – Taking the Green Road' (SSP1) combined with 'High Emissions' Option c climate policy assumptions following the ScenarioMIP protocol
A6: SSP1 - High Emissions_d | B6: 'Sustainability – Taking the Green Road' (SSP1) combined with 'High Emissions' Option d climate policy assumptions following the ScenarioMIP protocol
A7: SSP1 - High Emissions_e | B7: 'Sustainability – Taking the Green Road' (SSP1) combined with 'High Emissions' Option e climate policy assumptions following the ScenarioMIP protocol
A8: SSP1 - High Emissions_f | B8: 'Sustainability – Taking the Green Road' (SSP1) combined with 'High Emissions' Option f climate policy assumptions following the ScenarioMIP protocol
A9: SSP1 - High Emissions_g | B9: 'Sustainability – Taking the Green Road' (SSP1) combined with 'High Emissions' Option g climate policy assumptions following the ScenarioMIP protocol
A10: SSP1 - High Emissions_h | B10: 'Sustainability – Taking the Green Road' (SSP1) combined with 'High Emissions' Option h climate policy assumptions following the ScenarioMIP protocol
A11: SSP1 - High Emissions_i | B11: 'Sustainability – Taking the Green Road' (SSP1) combined with 'High Emissions' Option i climate policy assumptions following the ScenarioMIP protocol
A12: SSP1 - High Emissions_j | B12: 'Sustainability – Taking the Green Road' (SSP1) combined with 'High Emissions' Option j climate policy assumptions following the ScenarioMIP protocol
... A911: SSP5 - Very Low Emissions_z | B911: 'Fossil-fueled Development – Taking the Highway' (SSP5) combined with 'Very Low Emissions' Option z climate policy assumptions following the ScenarioMIP protocol

Sheet data
A1: Model | B1: Scenario | C1: Region | D1: Variable | E1: Unit | F1: 2005 | G1: 2010 | H1: 2015 | I1: 2020 | J1: 2025 | K1: 2030 | L1: 2035 | M1: 2040 | N1: 2045 | O1: 2050 | P1: 2060 | Q1: 2070 | R1: 2080 | S1: 2090 | T1: 2100
A2: IMAGE | B2: SSP1_NO_GAP_ELEC | C2: BRA | D2: Emissions|CO2|Energy | E2: Mt CO2/yr | F2: 320.61008 | G2: 375.03436 | H2: 470.75158 | I2: 394.82118 | J2: 471.55022 | K2: 456.54876 | L2: 470.99871 | M2: 673.70969 | N2: 1045.4327 | O2: 1228.832 | P2: 1231.4086 | Q2: 1026.9047 | R2: 693.13494 | S2: 483.89952 | T2: 482.33421
A3: IMAGE | B3: SSP1_NO_GAP_ELEC | C3: CAN | D3: Emissions|CO2|Energy | E3: Mt CO2/yr | F3: 557.70878 | G3: 542.63181 | H3: 575.04185 | I3: 545.5593 | J3: 582.56698 | K3: 597.24903 | L3: 530.92309 | M3: 483.22851 | N3: 430.5576 | O3: 401.92057 | P3: 401.37056 | Q3: 431.36023 | R3: 464.46547 | S3: 441.84543 | T3: 424.32537
A4: IMAGE | B4: SSP1_NO_GAP_ELEC | C4: CEU | D4: Emissions|CO2|Energy | E4: Mt CO2/yr | F4: 751.82691 | G4: 756.48684 | H4: 714.08261 | I4: 692.84929 | J4: 753.61919 | K4: 778.05678 | L4: 692.15299 | M4: 594.94343 | N4: 473.9999 | O4: 398.71736 | P4: 361.10055 | Q4: 371.97343 | R4: 343.3924 | S4: 242.03773 | T4: 217.16086
A5: IMAGE | B5: SSP1_NO_GAP_ELEC | C5: CHN | D5: Emissions|CO2|Energy | E5: Mt CO2/yr | F5: 5929.6088 | G5: 8461.0716 | H5: 9738.1934 | I5: 10515.703 | J5: 10923.235 | K5: 10072.191 | L5: 9488.1857 | M5: 8686.8647 | N5: 7412.4084 | O5: 6165.7748 | P5: 4657.213 | Q5: 4081.2051 | R5: 3330.1454 | S5: 2995.5632 | T5: 2716.1155
A6: IMAGE | B6: SSP1_NO_GAP_ELEC | C6: EAF | D6: Emissions|CO2|Energy | E6: Mt CO2/yr | F6: 42.062753 | G6: 59.453861 | H6: 74.949273 | I6: 80.560847 | J6: 102.98944 | K6: 155.98715 | L6: 224.8011 | M6: 351.70384 | N6: 453.74266 | O6: 515.18719 | P6: 568.43382 | Q6: 480.43746 | R6: 641.43751 | S6: 748.76595 | T6: 879.63812
A7: IMAGE | B7: SSP1_NO_GAP_ELEC | C7: INDIA | D7: Emissions|CO2|Energy | E7: Mt CO2/yr | F7: 1065.1957 | G7: 1563.1102 | H7: 2030.115 | I7: 2068.4782 | J7: 2841.5722 | K7: 3253.3641 | L7: 3601.6036 | M7: 3917.375 | N7: 4083.1782 | O7: 4265.5764 | P7: 4994.9865 | Q7: 5635.3548 | R7: 6087.2496 | S7: 6504.8867 | T7: 6427.3512
A8: IMAGE | B8: SSP1_NO_GAP_ELEC | C8: INDO | D8: Emissions|CO2|Energy | E8: Mt CO2/yr | F8: 327.43232 | G8: 419.24776 | H8: 477.68635 | I8: 560.23222 | J8: 718.40122 | K8: 835.34806 | L8: 988.68295 | M8: 1144.9317 | N8: 1273.7512 | O8: 1371.9343 | P8: 1617.3139 | Q8: 1767.1137 | R8: 1792.5695 | S8: 1889.9012 | T8: 1882.0517
A9: IMAGE | B9: SSP1_NO_GAP_ELEC | C9: JAP | D9: Emissions|CO2|Energy | E9: Mt CO2/yr | F9: 1187.7723 | G9: 1125.0121 | H9: 1138.8146 | I9: 943.76658 | J9: 960.87383 | K9: 883.05471 | L9: 790.12595 | M9: 716.15534 | N9: 682.44329 | O9: 677.90324 | P9: 634.11481 | Q9: 623.39311 | R9: 604.47239 | S9: 500.37532 | T9: 377.30478
A10: IMAGE | B10: SSP1_NO_GAP_ELEC | C10: KOR | D10: Emissions|CO2|Energy | E10: Mt CO2/yr | F10: 528.66295 | G10: 614.13991 | H10: 633.48741 | I10: 601.59659 | J10: 600.28611 | K10: 602.83632 | L10: 566.75448 | M10: 514.46668 | N10: 466.01975 | O10: 456.51136 | P10: 428.00341 | Q10: 351.42472 | R10: 282.21387 | S10: 267.45322 | T10: 283.95907
A11: IMAGE | B11: SSP1_NO_GAP_ELEC | C11: ME | D11: Emissions|CO2|Energy | E11: Mt CO2/yr | F11: 1275.4618 | G11: 1614.2552 | H11: 1879.7915 | I11: 1968.5021 | J11: 2157.4241 | K11: 2263.7121 | L11: 2438.0766 | M11: 2452.6627 | N11: 2517.3162 | O11: 2551.2864 | P11: 2631.3125 | Q11: 2668.6752 | R11: 2456.6512 | S11: 2228.0921 | T11: 2031.2982
A12: IMAGE | B12: SSP1_NO_GAP_ELEC | C12: MEX | D12: Emissions|CO2|Energy | E12: Mt CO2/yr | F12: 447.34397 | G12: 466.65595 | H12: 479.08371 | I12: 378.59507 | J12: 470.63941 | K12: 472.21789 | L12: 481.95732 | M12: 542.56805 | N12: 421.39095 | O12: 407.58629 | P12: 457.41007 | Q12: 455.31089 | R12: 458.95631 | S12: 541.46142 | T12: 434.29869
A13: IMAGE | B13: SSP1_NO_GAP_ELEC | C13: NAF | D13: Emissions|CO2|Energy | E13: Mt CO2/yr | F13: 360.78778 | G13: 427.94437 | H13: 493.90918 | I13: 484.94342 | J13: 603.23266 | K13: 677.83248 | L13: 738.69471 | M13: 803.54926 | N13: 893.36865 | O13: 977.57436 | P13: 1084.5725 | Q13: 1202.8574 | R13: 1271.589 | S13: 1303.1945 | T13: 1202.512
... A2350: IMAGE | B2350: SSP1_NO_GAP_ELEC | C2350: World | D2350: Private consumption|Household | E2350: US$2005ppp/capita | F2350: 0 | G2350: 0 | H2350: 0 | I2350: 0 | J2350: 0 | K2350: 0 | L2350: 0 | M2350: 0 | N2350: 0 | O2350: 0 | P2350: 0 | Q2350: 0 | R2350: 0 | S2350: 0 | T2350: 0

Sheet Priority-Emissions
A1: Model | B1: Scenario | C1: Region | D1: Variable | E1: Unit | F1: 2005 | G1: 2010 | H1: 2015 | I1: 2020 | J1: 2021 | K1: 2022 | L1: 2023 | M1: 2024 | N1: 2025 | O1: 2030 | P1: 2035 | Q1: 2040 | R1: 2045 | S1: 2050 | T1: 2060 | U1: 2070 | V1: 2080 | W1: 2090 | X1: 2100
D2: Emissions|BC|Energy|Supply | E2: Mt BC/yr
D3: Emissions|CH4|Energy|Supply | E3: Mt CH4/yr
D4: Emissions|CO2|Energy|Supply | E4: Mt CO2/yr
D5: Emissions|CO|Energy|Supply | E5: Mt CO/yr
D6: Emissions|N2O|Energy|Supply | E6: kt N2O/yr
D7: Emissions|NH3|Energy|Supply | E7: Mt NH3/yr
D8: Emissions|NOx|Energy|Supply | E8: Mt NO2/yr
D9: Emissions|OC|Energy|Supply | E9: Mt OC/yr
D10: Emissions|Sulfur|Energy|Supply | E10: Mt SO2/yr
D11: Emissions|VOC|Energy|Supply | E11: Mt VOC/yr
D12: Emissions|BC|Energy|Demand|Industry | E12: Mt BC/yr
D13: Emissions|CH4|Energy|Demand|Industry | E13: Mt CH4/yr
... D163: Emissions|F-Gases | E163: Mt CO2-equiv/yr

Sheet Priority-Energy
A1: Model | B1: Scenario | C1: Region | D1: Variable | E1: Unit | F1: 2005 | G1: 2010 | H1: 2015 | I1: 2020 | J1: 2021 | K1: 2022 | L1: 2023 | M1: 2024 | N1: 2025 | O1: 2030 | P1: 2035 | Q1: 2040 | R1: 2045 | S1: 2050 | T1: 2060 | U1: 2070 | V1: 2080 | W1: 2090 | X1: 2100
D2: Capacity|Electricity|Biomass | E2: =VLOOKUP(D2,variable!$A$2:$D$12140,4,FALSE) -> GW
D3: Capacity|Electricity|Biomass|w/o CCS | E3: =VLOOKUP(D3,variable!$A$2:$D$12140,4,FALSE) -> GW
D4: Capacity|Electricity|Coal | E4: =VLOOKUP(D4,variable!$A$2:$D$12140,4,FALSE) -> GW
D5: Capacity|Electricity|Coal|w/o CCS | E5: =VLOOKUP(D5,variable!$A$2:$D$12140,4,FALSE) -> GW
D6: Capacity|Electricity|Gas | E6: =VLOOKUP(D6,variable!$A$2:$D$12140,4,FALSE) -> GW
D7: Capacity|Electricity|Gas|w/o CCS | E7: =VLOOKUP(D7,variable!$A$2:$D$12140,4,FALSE) -> GW
D8: Capacity|Electricity|Geothermal | E8: =VLOOKUP(D8,variable!$A$2:$D$12140,4,FALSE) -> GW
D9: Capacity|Electricity|Hydro | E9: =VLOOKUP(D9,variable!$A$2:$D$12140,4,FALSE) -> GW
D10: Capacity|Electricity|Nuclear | E10: =VLOOKUP(D10,variable!$A$2:$D$12140,4,FALSE) -> GW
D11: Capacity|Electricity|Oil | E11: =VLOOKUP(D11,variable!$A$2:$D$12140,4,FALSE) -> GW
D12: Capacity|Electricity|Oil|w/o CCS | E12: =VLOOKUP(D12,variable!$A$2:$D$12140,4,FALSE) -> GW
D13: Capacity|Electricity|Solar | E13: =VLOOKUP(D13,variable!$A$2:$D$12140,4,FALSE) -> GW
... D85: Carbon Capture|Geological Storage|Fossil | E85: =VLOOKUP(D85,variable!$A$2:$D$12140,4,FALSE) -> Mt CO2/yr

Sheet All Tier 1 & Priority
A1: Model | B1: Scenario | C1: Region | D1: Variable | E1: Unit | F1: 2005 | G1: 2010 | H1: 2015 | I1: 2020 | J1: 2025 | K1: 2030 | L1: 2035 | M1: 2040 | N1: 2045 | O1: 2050 | P1: 2060 | Q1: 2070 | R1: 2080 | S1: 2090 | T1: 2100
D2: Agricultural Demand | E2: million t DM/yr
D3: Agricultural Demand|Crops | E3: million t DM/yr
D4: Agricultural Demand|Crops|Bioenergy | E4: million t DM/yr
D5: Agricultural Demand|Crops|Bioenergy|2nd generation | E5: million t DM/yr
D6: Agricultural Demand|Livestock | E6: million t DM/yr
D7: Agricultural Production | E7: million t DM/yr
D8: Agricultural Production|Crops | E8: million t DM/yr
D9: Agricultural Production|Livestock | E9: million t DM/yr
D10: Capacity|Electricity | E10: GW
D11: Capacity|Electricity|Ammonia | E11: GW
D12: Capacity|Electricity|Biomass | E12: GW
D13: Capacity|Electricity|Biomass|w/ CCS | E13: GW
D14: Capacity|Electricity|Biomass|w/o CCS | E14: GW
D15: Capacity|Electricity|Coal | E15: =VLOOKUP(D15,variable!$A$2:$D$12140,4,FALSE) -> GW
D16: Capacity|Electricity|Coal|w/ CCS | E16: GW
D17: Capacity|Electricity|Coal|w/o CCS | E17: GW
D18: Capacity|Electricity|Fossil | E18: GW
D19: Capacity|Electricity|Fossil|w/ CCS | E19: GW
D20: Capacity|Electricity|Fossil|w/o CCS | E20: GW
D21: Capacity|Electricity|Gas | E21: GW
D22: Capacity|Electricity|Gas|w/ CCS | E22: GW
D23: Capacity|Electricity|Gas|w/o CCS | E23: GW
D24: Capacity|Electricity|Geothermal | E24: =VLOOKUP(D24,variable!$A$2:$D$12140,4,FALSE) -> GW
D25: Capacity|Electricity|Hydro | E25: =VLOOKUP(D25,variable!$A$2:$D$12140,4,FALSE) -> GW
D26: Capacity|Electricity|Hydrogen | E26: GW
D27: Capacity|Electricity|Non-Biomass Renewables | E27: GW
D28: Capacity|Electricity|Nuclear | E28: =VLOOKUP(D28,variable!$A$2:$D$12140,4,FALSE) -> GW
D29: Capacity|Electricity|Ocean | E29: GW
D30: Capacity|Electricity|Oil | E30: =VLOOKUP(D30,variable!$A$2:$D$12140,4,FALSE) -> GW
D31: Capacity|Electricity|Oil|w/ CCS | E31: GW
D32: Capacity|Electricity|Oil|w/o CCS | E32: =VLOOKUP(D32,variable!$A$2:$D$12140,4,FALSE) -> GW
D33: Capacity|Electricity|Other | E33: GW
D34: Capacity|Electricity|Solar | E34: =VLOOKUP(D34,variable!$A$2:$D$12140,4,FALSE) -> GW
D35: Capacity|Electricity|Solar|CSP | E35: GW
D36: Capacity|Electricity|Solar|PV | E36: GW
D37: Capacity|Electricity|Wind | E37: =VLOOKUP(D37,variable!$A$2:$D$12140,4,FALSE) -> GW
D38: Capacity|Electricity|Wind|Offshore | E38: GW
D39: Capacity|Electricity|Wind|Onshore | E39: GW
D40: Capital Cost|Electricity|Biomass | E40: =VLOOKUP(D40,variable!$A$2:$D$12140,4,FALSE) -> USD_2010/kW
D41: Capital Cost|Electricity|Coal | E41: =VLOOKUP(D41,variable!$A$2:$D$12140,4,FALSE) -> USD_2010/kW
D42: Capital Cost|Electricity|Gas | E42: =VLOOKUP(D42,variable!$A$2:$D$12140,4,FALSE) -> USD_2010/kW
D43: Capital Cost|Electricity|Nuclear | E43: =VLOOKUP(D43,variable!$A$2:$D$12140,4,FALSE) -> USD_2010/kW
D44: Capital Cost|Electricity|Solar | E44: =VLOOKUP(D44,variable!$A$2:$D$12140,4,FALSE) -> USD_2010/kW
D45: Capital Cost|Electricity|Solar|PV | E45: =VLOOKUP(D45,variable!$A$2:$D$12140,4,FALSE) -> USD_2010/kW
D46: Capital Cost|Electricity|Wind | E46: =VLOOKUP(D46,variable!$A$2:$D$12140,4,FALSE) -> USD_2010/kW
D47: Capital Cost|Electricity|Wind|Offshore | E47: =VLOOKUP(D47,variable!$A$2:$D$12140,4,FALSE) -> USD_2010/kW
D48: Capital Cost|Electricity|Wind|Onshore | E48: =VLOOKUP(D48,variable!$A$2:$D$12140,4,FALSE) -> USD_2010/kW
D49: Capital Cost|Hydrogen|Electricity | E49: =VLOOKUP(D49,variable!$A$2:$D$12140,4,FALSE) -> USD_2010/kW
D50: Capital Formation | E50: billion USD_2010/yr
D51: Carbon Capture | E51: Mt CO2/yr
D52: Carbon Capture|Direct Air Capture | E52: Mt CO2/yr
D53: Carbon Capture|Direct Ocean Capture | E53: Mt CO2/yr
D54: Carbon Capture|Energy | E54: Mt CO2/yr
D55: Carbon Capture|Energy|Biomass | E55: Mt CO2/yr
D56: Carbon Capture|Energy|Fossil | E56: Mt CO2/yr
D57: Carbon Capture|Energy|Synthetic Fuels | E57: Mt CO2/yr
D58: Carbon Capture|Energy|Synthetic Fuels|Carbon-Neutral | E58: Mt CO2/yr
D59: Carbon Capture|Energy|Synthetic Fuels|Fossil | E59: Mt CO2/yr
D60: Carbon Capture|Energy|Synthetic Fuels|Industrial Processes | E60: Mt CO2/yr
D61: Carbon Capture|Geological Storage | E61: =VLOOKUP(D61,variable!$A$2:$D$12140,4,FALSE) -> Mt CO2/yr
D62: Carbon Capture|Geological Storage|Biomass | E62: =VLOOKUP(D62,variable!$A$2:$D$12140,4,FALSE) -> Mt CO2/yr
D63: Carbon Capture|Geological Storage|Direct Air Capture | E63: =VLOOKUP(D63,variable!$A$2:$D$12140,4,FALSE) -> Mt CO2/yr
D64: Carbon Capture|Geological Storage|Direct Ocean Capture | E64: Mt CO2/yr
D65: Carbon Capture|Geological Storage|Fossil | E65: =VLOOKUP(D65,variable!$A$2:$D$12140,4,FALSE) -> Mt CO2/yr
D66: Carbon Capture|Geological Storage|Industrial Processes | E66: =VLOOKUP(D66,variable!$A$2:$D$12140,4,FALSE) -> Mt CO2/yr
D67: Carbon Capture|Geological Storage|Other Sources | E67: Mt CO2/yr
D68: Carbon Capture|Industrial Processes | E68: Mt CO2/yr
D69: Carbon Capture|Industrial Processes|Chemicals | E69: Mt CO2/yr
D70: Carbon Capture|Industrial Processes|Iron and Steel | E70: Mt CO2/yr
D71: Carbon Capture|Industrial Processes|Non-Ferrous Metals | E71: Mt CO2/yr
D72: Carbon Capture|Industrial Processes|Non-Metallic Minerals | E72: Mt CO2/yr
D73: Carbon Capture|Industrial Processes|Other Sector | E73: Mt CO2/yr
D74: Carbon Capture|Industrial Processes|Pulp and Paper | E74: Mt CO2/yr
D75: Carbon Capture|Leakage | E75: Mt CO2/yr
D76: Carbon Capture|Other Sources | E76: Mt CO2/yr
D77: Carbon Capture|Other Storage | E77: Mt CO2/yr
D78: Carbon Capture|Utilization | E78: Mt CO2/yr
... D171: Emissions|CO2|Energy|Demand|Other Sector | E171: Mt CO2/yr
D172: Emissions|CO2|Energy|Demand|Residential and Commercial | E172: =VLOOKUP(D172,variable!$A$2:$D$12140,4,FALSE) -> Mt CO2/yr
D173: Emissions|CO2|Energy|Demand|Residential and Commercial and AFOFI | E173: Mt CO2/yr
D174: Emissions|CO2|Energy|Demand|Transportation | E174: Mt CO2/yr
D175: Emissions|CO2|Energy|Demand|Transportation|Domestic|Aviation | E175: Mt CO2/yr
D176: Emissions|CO2|Energy|Supply | E176: Mt CO2/yr
D177: Emissions|CO2|Industrial Processes | E177: Mt CO2/yr
D178: Emissions|CO2|Other | E178: Mt CO2/yr
D179: Emissions|CO2|Waste | E179: Mt CO2/yr
D180: Emissions|F-Gases | E180: Mt CO2-equiv/yr
D181: Emissions|HFC | E181: kt HFC134a-equiv/yr
D182: Emissions|HFC|HFC125 | E182: kt HFC125/yr
D183: Emissions|HFC|HFC134a | E183: kt HFC134a/yr
D184: Emissions|HFC|HFC143a | E184: kt HFC143a/yr
... D329: Final Energy|Bunkers | E329: EJ/yr
D330: Final Energy|Bunkers|Electricity | E330: =VLOOKUP(D330,variable!$A$2:$D$12140,4,FALSE) -> EJ/yr
D331: Final Energy|Bunkers|Gases | E331: =VLOOKUP(D331,variable!$A$2:$D$12140,4,FALSE) -> EJ/yr
D332: Final Energy|Bunkers|Heat | E332: EJ/yr
D333: Final Energy|Bunkers|Hydrogen | E333: =VLOOKUP(D333,variable!$A$2:$D$12140,4,FALSE) -> EJ/yr
D334: Final Energy|Bunkers|International Aviation | E334: EJ/yr
D335: Final Energy|Bunkers|International Shipping | E335: EJ/yr
D336: Final Energy|Bunkers|Liquids | E336: =VLOOKUP(D336,variable!$A$2:$D$12140,4,FALSE) -> EJ/yr
...

Sheet All & Priority
A1: Model | B1: Scenario | C1: Region | D1: Variable | E1: Unit | F1: 2005 | G1: 2010 | H1: 2015 | I1: 2020 | J1: 2025 | K1: 2030 | L1: 2035 | M1: 2040 | N1: 2045 | O1: 2050 | P1: 2060 | Q1: 2070 | R1: 2080 | S1: 2090 | T1: 2100
D2: Agricultural Demand | E2: million t DM/yr
D3: Agricultural Demand|Crops | E3: million t DM/yr
D4: Agricultural Demand|Crops|Bioenergy | E4: million t DM/yr
D5: Agricultural Demand|Crops|Bioenergy|1st Generation | E5: million t DM/yr
D6: Agricultural Demand|Crops|Bioenergy|2nd generation | E6: million t DM/yr
D7: Agricultural Demand|Crops|Feed | E7: million t DM/yr
D8: Agricultural Demand|Crops|Feed|Cereals | E8: million t DM/yr
D9: Agricultural Demand|Crops|Feed|Oil Crops | E9: million t DM/yr
D10: Agricultural Demand|Crops|Feed|Other Crops | E10: million t DM/yr
D11: Agricultural Demand|Crops|Feed|Sugar Crops | E11: million t DM/yr
D12: Agricultural Demand|Crops|Food | E12: million t DM/yr
D13: Agricultural Demand|Crops|Food|Cereals | E13: million t DM/yr
... D7629: Emissions|VOC|Energy|Demand|Transportation|Domestic|Aviation | E7629: Mt VOC/yr

Sheet NOTES
A1: Worksheet | B1: Description | C1: Other
A2: data | B2: Sheet used by Reporting too to report outputs for ScenarioMIP scenario explorer
A3: Priority-Emissions | B3: Priority variables for Emissions reporting. Based on email by Jarmo Kikstra (11/12/2024) | C3: https://docs.google.com/spreadsheets/d/1HKfl21NX8wohPEHpHlmf5XithknPw8zjLpVe4MiOU9U/edit?gid=1877841403#gid=1877841403
A4: Priority-Energy | B4: Priority variables for Energy reporting. Based on email by Gunnar Luderer (16/12/2024)
A5: All Tier 1 & Priority | B5: Priority Variables (Emissions & Energy) as well as Tier 1 variables from variable worksheet
A6: All & Priority | B6: Priority Variables (Emissions & Energy) as well as all Variables (that also have units) from variable worksheet
